greenflow_cusignal_plugin/__init__.py
greenflow_cusignal_plugin/windows.py
greenflow_cusignal_plugin/convolution/__init__.py
greenflow_cusignal_plugin/convolution/convolve.py
greenflow_cusignal_plugin/convolution/convolve2d.py
greenflow_cusignal_plugin/convolution/correlate.py
greenflow_cusignal_plugin/convolution/correlate2d.py
greenflow_cusignal_plugin/convolution/fftconvolve.py
greenflow_cusignal_plugin/filtering/__init__.py
greenflow_cusignal_plugin/filtering/custom_filter_block.py
greenflow_cusignal_plugin/filtering/resample_poly.py
greenflow_cusignal_plugin/gensig/__init__.py
greenflow_cusignal_plugin/gensig/gensig.py
greenflow_cusignal_plugin/gensig/wavefilereader.py
greenflow_cusignal_plugin/spectral_analysis/__init__.py
greenflow_cusignal_plugin/spectral_analysis/welchpsd.py
greenflow_cusignal_plugin-1.0.dist-info/METADATA
greenflow_cusignal_plugin-1.0.dist-info/WHEEL
greenflow_cusignal_plugin-1.0.dist-info/entry_points.txt
greenflow_cusignal_plugin-1.0.dist-info/top_level.txt
greenflow_cusignal_plugin-1.0.dist-info/RECORD
